aqui_brain_dump/__init__.py
aqui_brain_dump/__main__.py
aqui_brain_dump/backlinks_wikilinks.py
aqui_brain_dump/copy_files.py
aqui_brain_dump/extension_citations.py
aqui_brain_dump/extension_tags.py
aqui_brain_dump/extension_wikiimage.py
aqui_brain_dump/feed.rss
aqui_brain_dump/git_process.py
aqui_brain_dump/note.py
aqui_brain_dump/parse_bibliography.py
aqui_brain_dump/sitemap.xml
aqui_brain_dump/util.py
aqui_brain_dump-1.0.8.data/data/feed.rss
aqui_brain_dump-1.0.8.data/data/sitemap.xml
aqui_brain_dump-1.0.8.dist-info/METADATA
aqui_brain_dump-1.0.8.dist-info/WHEEL
aqui_brain_dump-1.0.8.dist-info/entry_points.txt
aqui_brain_dump-1.0.8.dist-info/top_level.txt
aqui_brain_dump-1.0.8.dist-info/RECORD
