Metadata-Version: 2.4
Name: aqui_brain_dump
Version: 1.0.8
Summary: Compile a set of notes into a browseable website
Home-page: https://github.com/aquilesC/static_website_builder
Author: Aquiles Carattino
Author-email: Aquiles Carattino <aqui.carattino@gmail.com>
License: Copyright 2021 Aquiles Carattino
Project-URL: Homepage, https://github.com/aquilesC/static_website_builder
Keywords: feed,reader,tutorial
Classifier: License :: OSI Approved :: MIT License
Classifier: Programming Language :: Python
Classifier: Programming Language :: Python :: 3
Requires-Python: >=3.8
Requires-Dist: beautifulsoup4==4.11.1
Requires-Dist: Jinja2==3.1.4
Requires-Dist: Markdown==3.7
Requires-Dist: markdown-checklist==0.4.4
Requires-Dist: MarkupSafe==2.1.1
Requires-Dist: md4mathjax==0.1.3
Requires-Dist: pyembed==1.3.3
Requires-Dist: pyembed-markdown==1.1.0
Requires-Dist: python-frontmatter==1.1.0
Requires-Dist: PyYAML==6.0.2
Requires-Dist: text-unidecode==1.3
Requires-Dist: setuptools==75.1.0
Dynamic: author
Dynamic: home-page
